HISTORY.rst
LICENSE
MANIFEST.in
README.rst
requirements-tests.txt
requirements.txt
setup.py
docker_ssh/__init__.py
docker_ssh/__main__.py
docker_ssh/cli.py
docker_ssh.egg-info/PKG-INFO
docker_ssh.egg-info/SOURCES.txt
docker_ssh.egg-info/dependency_links.txt
docker_ssh.egg-info/entry_points.txt
docker_ssh.egg-info/top_level.txt