Metadata-Version: 1.1
Name: docker-ssh
Version: 0.0.2
Summary: Python docker SSH tunnel
Home-page: https://github.com/andreycizov/python-docker_ssh
Author: Andrey Cizov
Author-email: acizov@gmail.com
License: UNKNOWN
Platform: UNKNOWN
Classifier: Development Status :: 2 - Pre-Alpha
Classifier: Intended Audience :: Developers
Classifier: License :: OSI Approved :: Apache Software License
Classifier: Natural Language :: English
Classifier: Programming Language :: Python :: 3.6
